fanbookbotapi/__init__.py
fanbookbotapi/api.py
fanbookbotapi/apilist.py
fanbookbotapi/botWs.py
fanbookbotapi/get_signature.py
fanbookbotapi/test.py
fanbookbotapi/userapi.py
fanbookbotapi-1.2.8.dist-info/METADATA
fanbookbotapi-1.2.8.dist-info/WHEEL
fanbookbotapi-1.2.8.dist-info/top_level.txt
fanbookbotapi-1.2.8.dist-info/RECORD
