Metadata-Version: 2.1
Name: fanbookbotapi
Version: 1.2.8
Summary: fanbook bot api
Home-page: https://github.com/fanbook-wangdage/fanbookbotapi/
Author: wangdage
Author-email: fanbookwdg1122@outlook.com
Classifier: Programming Language :: Python :: 3
Classifier: License :: OSI Approved :: MIT License
Classifier: Operating System :: OS Independent
Requires-Python: >=3.6
Requires-Dist: requests
Requires-Dist: coloredlogs
Requires-Dist: websocket-client
Requires-Dist: pygments
Requires-Dist: colorama
